README.md
setup.py
Voltra/__init__.py
Voltra/client.py
Voltra.api.egg-info/PKG-INFO
Voltra.api.egg-info/SOURCES.txt
Voltra.api.egg-info/dependency_links.txt
Voltra.api.egg-info/requires.txt
Voltra.api.egg-info/top_level.txt