Metadata-Version: 2.1
Name: Voltra.api
Version: 0.0.0
Summary: Voltra api but in python -_-
Home-page: UNKNOWN
Author: sldless
License: MIT
Platform: UNKNOWN
Classifier: Programming Language :: Python :: 3
Classifier: License :: OSI Approved :: MIT License
Classifier: Operating System :: OS Independent
Requires-Python: >=3.6
